guidemarks/__init__.py
guidemarks-0.0.1.dist-info/METADATA
guidemarks-0.0.1.dist-info/WHEEL
guidemarks-0.0.1.dist-info/entry_points.txt
guidemarks-0.0.1.dist-info/top_level.txt
guidemarks-0.0.1.dist-info/RECORD
